hipisejm/__init__.py
hipisejm-0.1.1.data/scripts/parser-parse-pdf.py
tests/__init__.py
hipisejm-0.1.1.dist-info/LICENSE
hipisejm-0.1.1.dist-info/METADATA
hipisejm-0.1.1.dist-info/WHEEL
hipisejm-0.1.1.dist-info/top_level.txt
hipisejm-0.1.1.dist-info/RECORD
