Metadata-Version: 2.1
Name: hipisejm
Version: 0.1.1
Summary: Parse Polish Sejm transcripts to machine readable corpus
Author: Marcin Walas
Author-email: kontakt@marcinwalas.pl
Classifier: Programming Language :: Python :: 3
License-File: LICENSE
Requires-Dist: pytest
Requires-Dist: pandas
Requires-Dist: numpy
Requires-Dist: pypdf
